{"cameraMode":{"drawMode":0,"name":"Shaded","section":"Shading Mode"},"sceneLighting":false,"audioPlay":false,"sceneViewState":{"m_AlwaysRefresh":false,"showFog":true,"showSkybox":false,"showFlares":true,"showImageEffects":true,"showParticleSystems":true,"showVisualEffectGraphs":true,"m_FxEnabled":true},"in2DMode":false,"pivot":{"x":6.150000095367432,"y":1.9613990783691407,"z":-32.5},"rotation":{"x":-0.1811930239200592,"y":-0.6260790228843689,"z":0.15215133130550385,"w":-0.7433035969734192},"size":13.037550926208496,"orthographic":false}